cacabplot/__init__.py
cacabplot/main.py
cacabplot-0.0.8.post1.dist-info/LICENCE
cacabplot-0.0.8.post1.dist-info/METADATA
cacabplot-0.0.8.post1.dist-info/WHEEL
cacabplot-0.0.8.post1.dist-info/top_level.txt
cacabplot-0.0.8.post1.dist-info/RECORD
