Metadata-Version: 2.1
Name: cacabplot
Version: 0.0.8.post1
Summary: A plottings tool package
Author-email: Casper Chris Adriaan Bekkers <casperbekkers2@hotmail.com>
Requires-Python: >=3.9
License-File: LICENCE
